.DS_Store
classy_django_datatables-1.0.8.dist-info/METADATA
classy_django_datatables-1.0.8.dist-info/RECORD
classy_django_datatables-1.0.8.dist-info/WHEEL
classy_django_datatables-1.0.8.dist-info/top_level.txt
django_datatables/.DS_Store
django_datatables/__init__.py
django_datatables/column.py
django_datatables/datatable.py
django_datatables/datatable_meta.py
django_datatables/excel.py
django_datatables/mixins.py
django_datatables/urls.py
django_datatables/views.py
django_datatables/templates/.DS_Store
django_datatables/templates/django_datatables/table.html
