Metadata-Version: 2.1
Name: classy-django-datatables
Version: 1.0.8
Summary: Create datatables quickly for django models.
Home-page: https://github.com/scuml/django-datatables
Author: Stephen Mitchell
Author-email: stephen@echodot.com
License: Apache
Platform: UNKNOWN
Classifier: Development Status :: 5 - Production/Stable
Classifier: Intended Audience :: Developers
Classifier: Natural Language :: English
Classifier: Topic :: Internet :: WWW/HTTP
Classifier: License :: OSI Approved :: Apache Software License
Classifier: Programming Language :: Python
Classifier: Programming Language :: Python :: 3.6
Classifier: Programming Language :: Python :: 3.7
Requires-Python: >=3.6
Requires-Dist: django (>=2)
Requires-Dist: pyquerystring
